setup.py
wymypy/__init__.py
wymypy/__main__.py
wymypy/app.py
wymypy/libs/__init__.py
wymypy/libs/flask.py
wymypy/libs/mpdclient.py
wymypy/libs/mpdsafe.py
wymypy/plugins/__init__.py
wymypy/plugins/cisco.py
wymypy/plugins/iradio.py
wymypy/plugins/library.py
wymypy/plugins/pandora2.py
wymypy/plugins/player.py
wymypy/plugins/playlists.py
wymypy/plugins/search.py
wymypy/static/jquery-1.10.2.min.js
wymypy/static/main.css
wymypy/static/main.js
wymypy/templates/main.html
wymypy/templates/player.html
wymypy_ng.egg-info/PKG-INFO
wymypy_ng.egg-info/SOURCES.txt
wymypy_ng.egg-info/dependency_links.txt
wymypy_ng.egg-info/entry_points.txt
wymypy_ng.egg-info/requires.txt
wymypy_ng.egg-info/top_level.txt