Metadata-Version: 1.0
Name: wymypy-ng
Version: 2.1
Summary: Simple web interface for controlling MPD
Home-page: http://www.02strich.de/
Author: Stefan Richter
Author-email: stefan@02strich.de
License: UNKNOWN
Platform: UNKNOWN
